examples/__init__.py
examples/echo_http/__init__.py
examples/echo_http/echo_http.py
examples/echo_upi/__init__.py
examples/echo_upi/upi_client.py
examples/echo_upi/upi_server.py
examples/iris_http/__init__.py
examples/iris_http/iris_http.py
pyfuncserver/__init__.py
pyfuncserver/__main__.py
pyfuncserver/config.py
pyfuncserver/server.py
pyfuncserver/version.py
pyfuncserver/metrics/__init__.py
pyfuncserver/metrics/handler.py
pyfuncserver/metrics/pusher.py
pyfuncserver/model/__init__.py
pyfuncserver/model/model.py
pyfuncserver/protocol/__init__.py
pyfuncserver/protocol/rest/__init__.py
pyfuncserver/protocol/rest/handler.py
pyfuncserver/protocol/rest/server.py
pyfuncserver/protocol/upi/__init__.py
pyfuncserver/protocol/upi/server.py
pyfuncserver/publisher/__init__.py
pyfuncserver/publisher/kafka.py
pyfuncserver/publisher/publisher.py
pyfuncserver/sampler/__init__.py
pyfuncserver/sampler/sampler.py
pyfuncserver/utils/__init__.py
pyfuncserver/utils/contants.py
pyfuncserver/utils/converter.py
test/publisher/__init__.py
test/publisher/test_kafka.py
test/publisher/test_publisher.py
test/sampler/__init__.py
test/sampler/test_sampler.py
test/util/__init__.py
test/util/test_converter.py
merlin_pyfunc_server-0.49.4.dist-info/METADATA
merlin_pyfunc_server-0.49.4.dist-info/WHEEL
merlin_pyfunc_server-0.49.4.dist-info/entry_points.txt
merlin_pyfunc_server-0.49.4.dist-info/top_level.txt
merlin_pyfunc_server-0.49.4.dist-info/RECORD
