Metadata-Version: 2.1
Name: merlin-pyfunc-server
Version: 0.49.4
Summary: Model Server implementation for Merlin PyFunc model
Author-email: merlin-dev@gojek.com
Requires-Python: >=3.9,<3.11
Requires-Dist: argparse>=1.4.0
Requires-Dist: caraml-upi-protos>=0.3.4
Requires-Dist: cloudpickle==2.0.0
Requires-Dist: confluent-kafka==2.3.0
Requires-Dist: grpcio-health-checking
Requires-Dist: grpcio-reflection
Requires-Dist: merlin-sdk==0.49.4
Requires-Dist: numpy>=1.8.2
Requires-Dist: orjson>=2.6.8
Requires-Dist: prometheus-client
Requires-Dist: setuptools<75
Requires-Dist: tornado
Requires-Dist: uvloop
Provides-Extra: test
Requires-Dist: joblib<1.2.0,>=0.13.0; extra == "test"
Requires-Dist: mypy; extra == "test"
Requires-Dist: pytest-benchmark; extra == "test"
Requires-Dist: pytest-tornasync; extra == "test"
Requires-Dist: pytest; extra == "test"
Requires-Dist: requests; extra == "test"
Requires-Dist: scikit-learn>=1.1.2; extra == "test"
Requires-Dist: types-protobuf; extra == "test"
Requires-Dist: types-requests; extra == "test"
Requires-Dist: xgboost==1.6.2; extra == "test"
